<?xml version="1.0" encoding="UTF-8" standalone="yes"?>
<AssignMessage async="false" continueOnError="false" enabled="true" name="AM-SetCustomDimensionsForRefreshToken">
    <DisplayName>AM-SetCustomDimensionsForRefreshToken</DisplayName>
    <FaultRules/>
    <Properties/>
    <AssignVariable>
        <Name>customerPPId</Name>
        <Ref>oauthv2refreshtoken.OAInfo-RetrieveRefreshTokenDetails.accesstoken.customerPPId</Ref>
    </AssignVariable>
    <AssignVariable>
        <Name>tokenOp</Name>
        <Value>refresh</Value>
    </AssignVariable>
    <IgnoreUnresolvedVariables>true</IgnoreUnresolvedVariables>
    <AssignTo transport="http" createNew="false"/>
</AssignMessage>